dmccodegui/__init__.py
dmccodegui/app_state.py
dmccodegui/controller.py
dmccodegui/main.py
dmccodegui/assets/images/arrow-down-red.png
dmccodegui/assets/images/arrow-left-orange.png
dmccodegui/assets/images/arrow-left-red.png
dmccodegui/assets/images/arrow-right-blue.png
dmccodegui/assets/images/arrow-right-green.png
dmccodegui/assets/images/arrow-up-green.png
dmccodegui/screens/__init__.py
dmccodegui/screens/arrays.py
dmccodegui/screens/rest.py
dmccodegui/screens/setup.py
dmccodegui/screens/start.py
dmccodegui/ui/arrays.kv
dmccodegui/ui/base.kv
dmccodegui/ui/edges.kv
dmccodegui/ui/rest.kv
dmccodegui/ui/setup.kv
dmccodegui/ui/start.kv
dmccodegui/ui/theme.kv
dmccodegui/utils/jobs.py
dmccodegui/utils/transport.py
dmccodegui-0.1.0.dist-info/METADATA
dmccodegui-0.1.0.dist-info/WHEEL
dmccodegui-0.1.0.dist-info/entry_points.txt
dmccodegui-0.1.0.dist-info/top_level.txt
dmccodegui-0.1.0.dist-info/RECORD
