Metadata-Version: 2.4
Name: dmccodegui
Version: 0.1.0
Summary: Kivy GUI for Galil DMC controller - designed for Raspberry Pi deployment
Author-email: Your Name <your.email@example.com>
Maintainer-email: Your Name <your.email@example.com>
License: Proprietary
Project-URL: Homepage, https://github.com/yourusername/dmccodegui
Project-URL: Repository, https://github.com/yourusername/dmccodegui
Project-URL: Documentation, https://github.com/yourusername/dmccodegui#readme
Project-URL: Bug Tracker, https://github.com/yourusername/dmccodegui/issues
Keywords: kivy,gui,galil,dmc,controller,raspberry-pi,industrial,automation,embedded
Classifier: Development Status :: 4 - Beta
Classifier: Intended Audience :: Manufacturing
Classifier: Intended Audience :: Developers
Classifier: Topic :: Scientific/Engineering
Classifier: Topic :: Software Development :: User Interfaces
Classifier: Topic :: System :: Hardware :: Hardware Drivers
Classifier: Programming Language :: Python :: 3
Classifier: Programming Language :: Python :: 3.10
Classifier: Programming Language :: Python :: 3.11
Classifier: Programming Language :: Python :: 3.12
Classifier: Operating System :: POSIX :: Linux
Classifier: Environment :: X11 Applications
Requires-Python: >=3.10
Requires-Dist: kivy>=2.2.0
Provides-Extra: dev
Requires-Dist: pytest>=7.0; extra == "dev"
Requires-Dist: pytest-cov; extra == "dev"
Requires-Dist: black; extra == "dev"
Requires-Dist: flake8; extra == "dev"
Requires-Dist: mypy; extra == "dev"
Provides-Extra: test
Requires-Dist: pytest-mock; extra == "test"
Requires-Dist: pytest-timeout; extra == "test"
